patch/__init__.py
patch/core.py
patch/error_handler.py
patch/exceptions.py
patch/interpreter.py
patch/objects.py
patch/version.py
patch/extensions/__init__.py
patch/extensions/mod/VecStim.mod
nrn_patch-7.2.1.dist-info/entry_points.txt
nrn_patch-7.2.1.dist-info/licenses/LICENSE
nrn_patch-7.2.1.dist-info/WHEEL
nrn_patch-7.2.1.dist-info/METADATA
nrn_patch-7.2.1.dist-info/RECORD
