Metadata-Version: 2.4
Name: nrn-patch
Version: 7.2.1
Summary: Quality of life patch for the NEURON simulator.
Author-email: Robin De Schepper <robin@alexandria.sc>
Requires-Python: >=3.10,<4
Classifier: License :: OSI Approved :: GNU General Public License v3 or later (GPLv3+)
License-File: LICENSE
Requires-Dist: nmodl-glia[neuron]~=7.0
Requires-Dist: packaging~=24.0
Requires-Dist: errr~=1.2
Requires-Dist: numpy~=1.21
Requires-Dist: NEURON>=9.0; sys_platform != 'win32'
Requires-Dist: mpi4py~=3.0 ; extra == "parallel"
Provides-Extra: parallel
